setup.py
plugins/__init__.py
plugins/bice.py
plugins/greet.py
plugins/kick.py
plugins/slap.py
plugins/spotify.py
plugins/urltitle.py
plugins/seen/__init__.py
plugins/seen/models.py
plugins/urllogger/__init__.py
plugins/urllogger/models.py
pycri/__init__.py
pycri/core.py
pycri.egg-info/PKG-INFO
pycri.egg-info/SOURCES.txt
pycri.egg-info/dependency_links.txt
pycri.egg-info/requires.txt
pycri.egg-info/top_level.txt
pycri/plugins/__init__.py
pycri/plugins/core.py
pycri/plugins/dice.py
pycri/utils/__init__.py
pycri/utils/encoding.py
pycri/utils/timeconversion.py